README.md
setup.py
pulumiverse_vra/__init__.py
pulumiverse_vra/_utilities.py
pulumiverse_vra/provider.py
pulumiverse_vra/pulumi-plugin.json
pulumiverse_vra/py.typed
pulumiverse_vra.egg-info/PKG-INFO
pulumiverse_vra.egg-info/SOURCES.txt
pulumiverse_vra.egg-info/dependency_links.txt
pulumiverse_vra.egg-info/not-zip-safe
pulumiverse_vra.egg-info/requires.txt
pulumiverse_vra.egg-info/top_level.txt
pulumiverse_vra/blockdevice/__init__.py
pulumiverse_vra/blockdevice/_inputs.py
pulumiverse_vra/blockdevice/block_device.py
pulumiverse_vra/blockdevice/get_block_device.py
pulumiverse_vra/blockdevice/get_snapshots.py
pulumiverse_vra/blockdevice/outputs.py
pulumiverse_vra/blockdevice/snapshot.py
pulumiverse_vra/blueprint/__init__.py
pulumiverse_vra/blueprint/_inputs.py
pulumiverse_vra/blueprint/blueprint.py
pulumiverse_vra/blueprint/blueprint_version.py
pulumiverse_vra/blueprint/get_blueprint.py
pulumiverse_vra/blueprint/get_version.py
pulumiverse_vra/blueprint/outputs.py
pulumiverse_vra/catalog/__init__.py
pulumiverse_vra/catalog/_inputs.py
pulumiverse_vra/catalog/get_item.py
pulumiverse_vra/catalog/get_item_entitlement.py
pulumiverse_vra/catalog/get_source_blueprint.py
pulumiverse_vra/catalog/get_source_entitlement.py
pulumiverse_vra/catalog/item_entitlement.py
pulumiverse_vra/catalog/outputs.py
pulumiverse_vra/catalog/source_blueprint.py
pulumiverse_vra/catalog/source_entitlement.py
pulumiverse_vra/cloudaccount/__init__.py
pulumiverse_vra/cloudaccount/_inputs.py
pulumiverse_vra/cloudaccount/aws.py
pulumiverse_vra/cloudaccount/azure.py
pulumiverse_vra/cloudaccount/gcp.py
pulumiverse_vra/cloudaccount/get_aws.py
pulumiverse_vra/cloudaccount/get_azure.py
pulumiverse_vra/cloudaccount/get_gcp.py
pulumiverse_vra/cloudaccount/get_nsxt.py
pulumiverse_vra/cloudaccount/get_nsxv.py
pulumiverse_vra/cloudaccount/get_v_sphere.py
pulumiverse_vra/cloudaccount/get_vmc.py
pulumiverse_vra/cloudaccount/nsxt.py
pulumiverse_vra/cloudaccount/nsxv.py
pulumiverse_vra/cloudaccount/outputs.py
pulumiverse_vra/cloudaccount/v_sphere.py
pulumiverse_vra/cloudaccount/vmc.py
pulumiverse_vra/config/__init__.py
pulumiverse_vra/config/vars.py
pulumiverse_vra/contentsource/__init__.py
pulumiverse_vra/contentsource/_inputs.py
