Metadata-Version: 2.1
Name: pulumiverse-vra
Version: 0.2.0
Summary: A Pulumi package for creating and managing VMware VRA cloud resources.
Home-page: https://www.pulumi.com
License: Apache-2.0
Project-URL: Repository, https://github.com/pulumiverse/pulumi-vra
Keywords: pulumi vra category/cloud
Platform: UNKNOWN
